iocsv
