Metadata-Version: 1.0
Name: iocsv
Version: 1.0
Summary: Python package to read and write csv files
Home-page: https://github.com/fpgdubost/iocsv
Author: Florian Dubost
Author-email: floriandubost1@gmail.com
License: GNU General Public License
Platform: UNKNOWN
